odoo/addons/purchase_order_line_menu/README.rst
odoo/addons/purchase_order_line_menu/__init__.py
odoo/addons/purchase_order_line_menu/__manifest__.py
odoo/addons/purchase_order_line_menu/i18n/es.po
odoo/addons/purchase_order_line_menu/i18n/fr_FR.po
odoo/addons/purchase_order_line_menu/i18n/it.po
odoo/addons/purchase_order_line_menu/i18n/pt_BR.po
odoo/addons/purchase_order_line_menu/i18n/purchase_order_line_menu.pot
odoo/addons/purchase_order_line_menu/readme/CONTRIBUTORS.rst
odoo/addons/purchase_order_line_menu/readme/DESCRIPTION.rst
odoo/addons/purchase_order_line_menu/readme/USAGE.rst
odoo/addons/purchase_order_line_menu/static/description/icon.png
odoo/addons/purchase_order_line_menu/static/description/index.html
odoo/addons/purchase_order_line_menu/views/purchase_order_line_views.xml
odoo14_addon_purchase_order_line_menu-14.0.1.0.1.dev13.dist-info/METADATA
odoo14_addon_purchase_order_line_menu-14.0.1.0.1.dev13.dist-info/WHEEL
odoo14_addon_purchase_order_line_menu-14.0.1.0.1.dev13.dist-info/top_level.txt
odoo14_addon_purchase_order_line_menu-14.0.1.0.1.dev13.dist-info/RECORD
